[
  {
    "cardType": "hero-site",
    "id": "tw-421",
    "name": "Rivendell",
    "siteType": "haven",
    "sitePath": [],
    "nearestHaven": "",
    "playableResources": [],
    "automaticAttacks": [],
    "text": "Site Path From Lórien: Wilderness/Border-land/Wilderness/Wilderness. Site Path From Grey Havens: Free-domain/Wilderness/Wilderness."
  },
  {
    "cardType": "hero-site",
    "id": "tw-408",
    "name": "Lórien",
    "siteType": "haven",
    "sitePath": [],
    "nearestHaven": "",
    "playableResources": [],
    "automaticAttacks": [],
    "text": "Site Path From Rivendell: Wilderness/Wilderness/Border-land/Wilderness. Site Path From Edhellond: Wilderness/Border-land/Free-domain/Free-domain/Border-land/Wilderness."
  },
  {
    "cardType": "hero-site",
    "id": "tw-413",
    "name": "Moria",
    "siteType": "shadow-hold",
    "sitePath": ["wilderness", "wilderness"],
    "nearestHaven": "Lórien",
    "playableResources": ["minor", "major", "greater", "gold-ring"],
    "automaticAttacks": [{ "creatureType": "Orcs", "strikes": 4, "prowess": 7 }],
    "text": "Playable: Items (minor, major, greater, gold ring). Automatic-attacks: Orcs — 4 strikes with 7 prowess."
  },
  {
    "cardType": "hero-site",
    "id": "tw-412",
    "name": "Minas Tirith",
    "siteType": "free-hold",
    "sitePath": ["wilderness", "border", "free"],
    "nearestHaven": "Lórien",
    "playableResources": ["faction"],
    "automaticAttacks": [],
    "text": ""
  },
  {
    "cardType": "hero-site",
    "id": "tw-414",
    "name": "Mount Doom",
    "siteType": "shadow-hold",
    "sitePath": ["wilderness", "border", "free", "wilderness", "shadow", "dark"],
    "nearestHaven": "Lórien",
    "playableResources": [],
    "automaticAttacks": [],
    "text": "Any company moving to this site has its hazard limit increased by 2 and hazard creatures may always be played keyed to the site regardless of any other cards played."
  }
]
